{
    "road_distance_raw": {
        "features": [
            {
                "properties": {
                    "summary": {
                        "distance": 119332.9,
                        "duration": 5684.9
                    }
                },
                "geometry": {
                    "coordinates": [
                        [
                            -90.721561,
                            35.551499
                        ],
                        [
                            -90.721532,
                            35.553494
                        ],
                        [
                            -90.721537,
                            35.555193
                        ],
                        [
                            -90.721574,
                            35.555464
                        ],
                        [
                            -90.721638,
                            35.555754
                        ],
                        [
                            -90.721727,
                            35.556013
                        ],
                        [
                            -90.721837,
                            35.556253
                        ],
                        [
                            -90.721991,
                            35.556506
                        ],
                        [
                            -90.722114,
                            35.556651
                        ],
                        [
                            -90.722237,
                            35.556807
                        ],
                        [
                            -90.722451,
                            35.557013
                        ],
                        [
                            -90.72281,
                            35.557302
                        ],
                        [
                            -90.72348,
                            35.557844
                        ],
                        [
                            -90.723706,
                            35.558066
                        ],
                        [
                            -90.723885,
                            35.55829
                        ],
                        [
                            -90.724027,
                            35.558504
                        ],
                        [
                            -90.72416,
                            35.558767
                        ],
                        [
                            -90.724256,
                            35.55897
                        ],
                        [
                            -90.724332,
                            35.559215
                        ],
                        [
                            -90.724381,
                            35.559525
                        ],
                        [
                            -90.724396,
                            35.56012
                        ],
                        [
                            -90.724386,
                            35.561059
                        ],
                        [
                            -90.724376,
                            35.561403
                        ],
                        [
                            -90.724324,
                            35.56334
                        ],
                        [
                            -90.724309,
                            35.563996
                        ],
                        [
                            -90.724295,
                            35.565182
                        ],
                        [
                            -90.722836,
                            35.565119
                        ],
                        [
                            -90.721292,
                            35.565038
                        ],
                        [
                            -90.720219,
                            35.564983
                        ],
                        [
                            -90.719847,
                            35.564948
                        ],
                        [
                            -90.719495,
                            35.564884
                        ],
                        [
                            -90.719256,
                            35.564832
                        ],
                        [
                            -90.717855,
                            35.564433
                        ],
                        [
                            -90.717215,
                            35.564244
                        ],
                        [
                            -90.716461,
                            35.564019
                        ],
                        [
                            -90.715903,
                            35.563854
                        ],
                        [
                            -90.715597,
                            35.563795
                        ],
                        [
                            -90.715331,
                            35.563766
                        ],
                        [
                            -90.715036,
                            35.563756
                        ],
                        [
                            -90.714805,
                            35.563765
                        ],
                        [
                            -90.712984,
                            35.563916
                        ],
                        [
                            -90.712416,
                            35.563895
                        ],
                        [
                            -90.711774,
                            35.563782
                        ],
                        [
                            -90.710665,
                            35.563544
                        ],
                        [
                            -90.709983,
                            35.563445
                        ],
                        [
                            -90.709296,
                            35.56337
                        ],
                        [
                            -90.708672,
                            35.563345
                        ],
                        [
                            -90.707928,
                            35.563299
                        ],
                        [
                            -90.705442,
                            35.563232
                        ],
                        [
                            -90.703971,
                            35.563212
                        ],
                        [
                            -90.703548,
                            35.563212
                        ],
                        [
                            -90.702881,
                            35.563198
                        ],
                        [
                            -90.701083,
                            35.5632
                        ],
                        [
                            -90.700765,
                            35.5632
                        ],
                        [
                            -90.70034,
                            35.563189
                        ],
                        [
                            -90.69512,
                            35.56315
                        ],
                        [
                            -90.692875,
                            35.563138
                        ],
                        [
                            -90.692114,
                            35.563119
                        ],
                        [
                            -90.69195,
                            35.563112
                        ],
                        [
                            -90.691322,
                            35.563039
                        ],
                        [
                            -90.690805,
                            35.562924
                        ],
                        [
                            -90.690424,
                            35.562807
                        ],
                        [
                            -90.687663,
                            35.56174
                        ],
                        [
                            -90.6866,
                            35.561336
                        ],
                        [
                            -90.685923,
                            35.561079
                        ],
                        [
                            -90.685548,
                            35.560978
                        ],
                        [
                            -90.685179,
                            35.560914
                        ],
                        [
                            -90.684722,
                            35.560876
                        ],
                        [
                            -90.684314,
                            35.560881
                        ],
                        [
                            -90.683949,
                            35.560916
                        ],
                        [
                            -90.683521,
                            35.561
                        ],
                        [
                            -90.683023,
                            35.561148
                        ],
                        [
                            -90.682617,
                            35.561316
                        ],
                        [
                            -90.682324,
                            35.561484
                        ],
                        [
                            -90.681984,
                            35.561748
                        ],
                        [
                            -90.681738,
                            35.561979
                        ],
                        [
                            -90.681429,
                            35.562359
                        ],
                        [
                            -90.681206,
                            35.562747
                        ],
                        [
                            -90.681108,
                            35.562965
                        ],
                        [
                            -90.680981,
                            35.563419
                        ],
                        [
                            -90.680846,
                            35.564589
                        ],
                        [
                            -90.680789,
                            35.564913
                        ],
                        [
                            -90.680668,
                            35.565231
                        ],
                        [
                            -90.680548,
                            35.565472
                        ],
                        [
                            -90.680211,
                            35.565975
                        ],
                        [
                            -90.679269,
                            35.566847
                        ],
                        [
                            -90.678614,
                            35.567427
                        ],
                        [
                            -90.678379,
                            35.5676
                        ],
                        [
                            -90.678129,
                            35.567735
                        ],
                        [
                            -90.677907,
                            35.567834
                        ],
                        [
                            -90.677628,
                            35.567907
                        ],
                        [
                            -90.677303,
                            35.567946
                        ],
                        [
                            -90.677012,
                            35.567944
                        ],
                        [
                            -90.676719,
                            35.567909
                        ],
                        [
                            -90.676426,
                            35.567832
                        ],
                        [
                            -90.676143,
                            35.567709
                        ],
                        [
                            -90.675813,
                            35.567529
                        ],
                        [
                            -90.674707,
                            35.566868
                        ],
                        [
                            -90.674387,
                            35.566716
                        ],
                        [
                            -90.674085,
                            35.566612
                        ],
                        [
                            -90.673782,
                            35.566568
                        ],
                        [
                            -90.673456,
                            35.566544
                        ],
                        [
                            -90.673118,
                            35.566568
                        ],
                        [
                            -90.67279,
                            35.566641
                        ],
                        [
                            -90.672497,
                            35.566759
                        ],
                        [
                            -90.671918,
                            35.567038
                        ],
                        [
                            -90.671559,
                            35.567173
                        ],
                        [
                            -90.67074,
                            35.567381
                        ],
                        [
                            -90.669081,
                            35.567757
                        ],
                        [
                            -90.668554,
                            35.567875
                        ],
                        [
                            -90.660195,
                            35.569757
                        ],
                        [
                            -90.659473,
                            35.569905
                        ],
                        [
                            -90.658863,
                            35.56999
                        ],
                        [
                            -90.658254,
                            35.570042
                        ],
                        [
                            -90.658117,
                            35.570046
                        ],
                        [
                            -90.657392,
                            35.570072
                        ],
                        [
                            -90.652045,
                            35.570101
                        ],
                        [
                            -90.643193,
                            35.570136
                        ],
                        [
                            -90.63871,
                            35.570102
                        ],
                        [
                            -90.633978,
                            35.570052
                        ],
                        [
                            -90.626043,
                            35.569969
                        ],
                        [
                            -90.625049,
                            35.569956
                        ],
                        [
                            -90.616564,
                            35.569847
                        ],
                        [
                            -90.616197,
                            35.569842
                        ],
                        [
                            -90.612863,
                            35.569802
                        ],
                        [
                            -90.612208,
                            35.56973
                        ],
                        [
                            -90.611401,
                            35.569537
                        ],
                        [
                            -90.610648,
                            35.569232
                        ],
                        [
                            -90.609973,
                            35.568824
                        ],
                        [
                            -90.609395,
                            35.568328
                        ],
                        [
                            -90.608932,
                            35.567756
                        ],
                        [
                            -90.608599,
                            35.567128
                        ],
                        [
                            -90.608414,
                            35.566523
                        ],
                        [
                            -90.608351,
                            35.56612
                        ],
                        [
                            -90.608347,
                            35.565248
                        ],
                        [
                            -90.608401,
                            35.561773
                        ],
                        [
                            -90.608443,
                            35.559107
                        ],
                        [
                            -90.608554,
                            35.552754
                        ],
                        [
                            -90.608547,
                            35.551547
                        ],
                        [
                            -90.608524,
                            35.550968
                        ],
                        [
                            -90.608464,
                            35.550618
                        ],
                        [
                            -90.608284,
                            35.550042
                        ],
                        [
                            -90.608151,
                            35.549726
                        ],
                        [
                            -90.607965,
                            35.549433
                        ],
                        [
                            -90.607655,
                            35.549023
                        ],
                        [
                            -90.607258,
                            35.548626
                        ],
                        [
                            -90.606806,
                            35.548277
                        ],
                        [
                            -90.606263,
                            35.547957
                        ],
                        [
                            -90.605921,
                            35.5478
                        ],
                        [
                            -90.605528,
                            35.54766
                        ],
                        [
                            -90.605083,
                            35.547537
                        ],
                        [
                            -90.604563,
                            35.54744
                        ],
                        [
                            -90.604262,
                            35.547397
                        ],
                        [
                            -90.603877,
                            35.54738
                        ],
                        [
                            -90.602219,
                            35.547375
                        ],
                        [
                            -90.600426,
                            35.547385
                        ],
                        [
                            -90.599921,
                            35.547387
                        ],
                        [
                            -90.599469,
                            35.547387
                        ],
                        [
                            -90.599031,
                            35.547387
                        ],
                        [
                            -90.596474,
                            35.547397
                        ],
                        [
                            -90.590961,
                            35.547394
                        ],
                        [
                            -90.590832,
                            35.547394
                        ],
                        [
                            -90.586351,
                            35.547185
                        ],
                        [
                            -90.577457,
                            35.546759
                        ],
                        [
                            -90.573025,
                            35.546543
                        ],
                        [
                            -90.568574,
                            35.546348
                        ],
                        [
                            -90.562856,
                            35.546097
                        ],
                        [
                            -90.555297,
                            35.545727
                        ],
                        [
                            -90.546349,
                            35.545303
                        ],
                        [
                            -90.53752,
                            35.544857
                        ],
                        [
                            -90.525197,
                            35.544306
                        ],
                        [
                            -90.519712,
                            35.544078
                        ],
                        [
                            -90.517186,
                            35.543982
                        ],
                        [
                            -90.513148,
                            35.543854
                        ],
                        [
                            -90.510862,
                            35.54377
                        ],
                        [
                            -90.503452,
                            35.543393
                        ],
                        [
                            -90.503253,
                            35.543395
                        ],
                        [
                            -90.503093,
                            35.543423
                        ],
                        [
                            -90.502942,
                            35.543473
                        ],
                        [
                            -90.502795,
                            35.543546
                        ],
                        [
                            -90.502689,
                            35.54364
                        ],
                        [
                            -90.50261,
                            35.543745
                        ],
                        [
                            -90.502557,
                            35.543853
                        ],
                        [
                            -90.502346,
                            35.544436
                        ],
                        [
                            -90.502263,
                            35.54459
                        ],
                        [
                            -90.502016,
                            35.544872
                        ],
                        [
                            -90.501801,
                            35.545043
                        ],
                        [
                            -90.501459,
                            35.545241
                        ],
                        [
                            -90.499103,
                            35.546344
                        ],
                        [
                            -90.498712,
                            35.546467
                        ],
                        [
                            -90.498687,
                            35.546474
                        ],
                        [
                            -90.498359,
                            35.54654
                        ],
                        [
                            -90.498387,
                            35.546468
                        ],
                        [
                            -90.498379,
                            35.546395
                        ],
                        [
                            -90.498346,
                            35.546347
                        ],
                        [
                            -90.496073,
                            35.543752
                        ],
                        [
                            -90.495206,
                            35.542684
                        ],
                        [
                            -90.494573,
                            35.541995
                        ],
                        [
                            -90.493566,
                            35.541112
                        ],
                        [
                            -90.492615,
                            35.540474
                        ],
                        [
                            -90.492221,
                            35.540246
                        ],
                        [
                            -90.491704,
                            35.53996
                        ],
                        [
                            -90.490583,
                            35.539514
                        ],
                        [
                            -90.488957,
                            35.538997
                        ],
                        [
                            -90.484929,
                            35.537757
                        ],
                        [
                            -90.482997,
                            35.537157
                        ],
                        [
                            -90.480298,
                            35.536325
                        ],
                        [
                            -90.478036,
                            35.535631
                        ],
                        [
                            -90.475426,
                            35.534825
                        ],
                        [
                            -90.471645,
                            35.533658
                        ],
                        [
                            -90.468511,
                            35.53269
                        ],
                        [
                            -90.466649,
                            35.532117
                        ],
                        [
                            -90.458815,
                            35.529703
                        ],
                        [
                            -90.457318,
                            35.529239
                        ],
                        [
                            -90.455097,
                            35.52854
                        ],
                        [
                            -90.453767,
                            35.528142
                        ],
                        [
                            -90.453003,
                            35.527981
                        ],
                        [
                            -90.452162,
                            35.527863
                        ],
                        [
                            -90.451226,
                            35.527835
                        ],
                        [
                            -90.443711,
                            35.527779
                        ],
                        [
                            -90.436486,
                            35.52769
                        ],
                        [
                            -90.435593,
                            35.527662
                        ],
                        [
                            -90.43499,
                            35.527592
                        ],
                        [
                            -90.434543,
                            35.527507
                        ],
                        [
                            -90.434042,
                            35.527379
                        ],
                        [
                            -90.433673,
                            35.527259
                        ],
                        [
                            -90.432596,
                            35.526828
                        ],
                        [
                            -90.427645,
                            35.52478
                        ],
                        [
                            -90.425528,
                            35.523899
                        ],
                        [
                            -90.424258,
                            35.523374
                        ],
                        [
                            -90.41893,
                            35.521169
                        ],
                        [
                            -90.417504,
                            35.520581
                        ],
                        [
                            -90.416692,
                            35.520297
                        ],
                        [
                            -90.415829,
                            35.520076
                        ],
                        [
                            -90.414962,
                            35.519925
                        ],
                        [
                            -90.414067,
                            35.519832
                        ],
                        [
                            -90.413184,
                            35.519805
                        ],
                        [
                            -90.406528,
                            35.519745
                        ],
                        [
                            -90.405515,
                            35.519732
                        ],
                        [
                            -90.404915,
                            35.519701
                        ],
                        [
                            -90.404429,
                            35.519637
                        ],
                        [
                            -90.403929,
                            35.519537
                        ],
                        [
                            -90.403434,
                            35.519399
                        ],
                        [
                            -90.402875,
                            35.519204
                        ],
                        [
                            -90.402426,
                            35.519013
                        ],
                        [
                            -90.402,
                            35.518793
                        ],
                        [
                            -90.401653,
                            35.518574
                        ],
                        [
                            -90.401263,
                            35.518286
                        ],
                        [
                            -90.400933,
                            35.518017
                        ],
                        [
                            -90.399784,
                            35.516955
                        ],
                        [
                            -90.398947,
                            35.516127
                        ],
                        [
                            -90.39761,
                            35.514943
                        ],
                        [
                            -90.396743,
                            35.514128
                        ],
                        [
                            -90.389464,
                            35.507398
                        ],
                        [
                            -90.387284,
                            35.505607
                        ],
                        [
                            -90.384734,
                            35.503259
                        ],
                        [
                            -90.384069,
                            35.502645
                        ],
                        [
                            -90.369627,
                            35.489218
                        ],
                        [
                            -90.361854,
                            35.482033
                        ],
                        [
                            -90.361379,
                            35.481632
                        ],
                        [
                            -90.360896,
                            35.481289
                        ],
                        [
                            -90.360442,
                            35.481019
                        ],
                        [
                            -90.359841,
                            35.480707
                        ],
                        [
                            -90.359231,
                            35.480456
                        ],
                        [
                            -90.35869,
                            35.480273
                        ],
                        [
                            -90.358148,
                            35.480138
                        ],
                        [
                            -90.35762,
                            35.48003
                        ],
                        [
                            -90.357183,
                            35.479969
                        ],
                        [
                            -90.356685,
                            35.479921
                        ],
                        [
                            -90.356132,
                            35.479896
                        ],
                        [
                            -90.354087,
                            35.479904
                        ],
                        [
                            -90.35334,
                            35.479882
                        ],
                        [
                            -90.352554,
                            35.479821
                        ],
                        [
                            -90.351952,
                            35.479746
                        ],
                        [
                            -90.351248,
                            35.479628
                        ],
                        [
                            -90.350648,
                            35.479499
                        ],
                        [
                            -90.349964,
                            35.479322
                        ],
                        [
                            -90.349,
                            35.479045
                        ],
                        [
                            -90.348396,
                            35.478865
                        ],
                        [
                            -90.345004,
                            35.47786
                        ],
                        [
                            -90.344017,
                            35.477556
                        ],
                        [
                            -90.343268,
                            35.477299
                        ],
                        [
                            -90.3425,
                            35.477002
                        ],
                        [
                            -90.341931,
                            35.476759
                        ],
                        [
                            -90.340904,
                            35.476268
                        ],
                        [
                            -90.330416,
                            35.471166
                        ],
                        [
                            -90.329206,
                            35.470566
                        ],
                        [
                            -90.328599,
                            35.47024
                        ],
                        [
                            -90.327999,
                            35.469842
                        ],
                        [
                            -90.327573,
                            35.469518
                        ],
                        [
                            -90.327065,
                            35.469084
                        ],
                        [
                            -90.326682,
                            35.468685
                        ],
                        [
                            -90.326069,
                            35.467968
                        ],
                        [
                            -90.321373,
                            35.462119
                        ],
                        [
                            -90.316118,
                            35.455509
                        ],
                        [
                            -90.315081,
                            35.453897
                        ],
                        [
                            -90.31402,
                            35.452633
                        ],
                        [
                            -90.312687,
                            35.451227
                        ],
                        [
                            -90.304821,
                            35.441345
                        ],
                        [
                            -90.304617,
                            35.441094
                        ],
                        [
                            -90.30221,
                            35.43808
                        ],
                        [
                            -90.299763,
                            35.435052
                        ],
                        [
                            -90.285641,
                            35.417324
                        ],
                        [
                            -90.285285,
                            35.416784
                        ],
                        [
                            -90.284857,
                            35.415918
                        ],
                        [
                            -90.284595,
                            35.415276
                        ],
                        [
                            -90.281246,
                            35.407931
                        ],
                        [
                            -90.278589,
                            35.402134
                        ],
                        [
                            -90.278446,
                            35.401818
                        ],
                        [
                            -90.276557,
                            35.397623
                        ],
                        [
                            -90.276289,
                            35.397068
                        ],
                        [
                            -90.275706,
                            35.395143
                        ],
                        [
                            -90.275589,
                            35.394687
                        ],
                        [
                            -90.275572,
                            35.394073
                        ],
                        [
                            -90.275656,
                            35.393614
                        ],
                        [
                            -90.275791,
                            35.393094
                        ],
                        [
                            -90.276333,
                            35.391165
                        ],
                        [
                            -90.276629,
                            35.390531
                        ],
                        [
                            -90.27699,
                            35.389955
                        ],
                        [
                            -90.277517,
                            35.38921
                        ],
                        [
                            -90.278105,
                            35.388494
                        ],
                        [
                            -90.27855,
                            35.387818
                        ],
                        [
                            -90.278681,
                            35.387566
                        ],
                        [
                            -90.278914,
                            35.387052
                        ],
                        [
                            -90.279108,
                            35.386531
                        ],
                        [
                            -90.279191,
                            35.386268
                        ],
                        [
                            -90.279387,
                            35.385396
                        ],
                        [
                            -90.279488,
                            35.384357
                        ],
                        [
                            -90.279602,
                            35.375858
                        ],
                        [
                            -90.279752,
                            35.369339
                        ],
                        [
                            -90.279834,
                            35.366326
                        ],
                        [
                            -90.279799,
                            35.365059
                        ],
                        [
                            -90.27986,
                            35.363327
                        ],
                        [
                            -90.279843,
                            35.362598
                        ],
                        [
                            -90.279782,
                            35.361871
                        ],
                        [
                            -90.279614,
                            35.360815
                        ],
                        [
                            -90.279353,
                            35.359772
                        ],
                        [
                            -90.279001,
                            35.358746
                        ],
                        [
                            -90.278546,
                            35.35764
                        ],
                        [
                            -90.27787,
                            35.356343
                        ],
                        [
                            -90.275662,
                            35.352223
                        ],
                        [
                            -90.275447,
                            35.351814
                        ],
                        [
                            -90.253535,
                            35.310644
                        ],
                        [
                            -90.249829,
                            35.303675
                        ],
                        [
                            -90.244437,
                            35.293543
                        ],
                        [
                            -90.241266,
                            35.287482
                        ],
                        [
                            -90.239068,
                            35.283334
                        ],
                        [
                            -90.234784,
                            35.275354
                        ],
                        [
                            -90.23027,
                            35.266819
                        ],
                        [
                            -90.22817,
                            35.262927
                        ],
                        [
                            -90.226439,
                            35.259672
                        ],
                        [
                            -90.221705,
                            35.25072
                        ],
                        [
                            -90.220889,
                            35.249255
                        ],
                        [
                            -90.220314,
                            35.24812
                        ],
                        [
                            -90.219835,
                            35.247238
                        ],
                        [
                            -90.219682,
                            35.246942
                        ],
                        [
                            -90.218661,
                            35.244988
                        ],
                        [
                            -90.218317,
                            35.244272
                        ],
                        [
                            -90.217854,
                            35.243183
                        ],
                        [
                            -90.217147,
                            35.241362
                        ],
                        [
                            -90.213577,
                            35.231183
                        ],
                        [
                            -90.211963,
                            35.226703
                        ],
                        [
                            -90.210679,
                            35.22299
                        ],
                        [
                            -90.209875,
                            35.220698
                        ],
                        [
                            -90.209582,
                            35.219909
                        ],
                        [
                            -90.20846,
                            35.21668
                        ],
                        [
                            -90.208092,
                            35.215582
                        ],
                        [
                            -90.207071,
                            35.212791
                        ],
                        [
                            -90.206619,
                            35.211454
                        ],
                        [
                            -90.205735,
                            35.208945
                        ],
                        [
                            -90.203809,
                            35.203555
                        ],
                        [
                            -90.202161,
                            35.198786
                        ],
                        [
                            -90.200851,
                            35.195067
                        ],
                        [
                            -90.199955,
                            35.192621
                        ],
                        [
                            -90.198621,
                            35.188748
                        ],
                        [
                            -90.198282,
                            35.187746
                        ],
                        [
                            -90.196642,
                            35.183203
                        ],
                        [
                            -90.195742,
                            35.180624
                        ],
                        [
                            -90.195278,
                            35.179272
                        ],
                        [
                            -90.194771,
                            35.177714
                        ],
                        [
                            -90.194572,
                            35.17661
                        ],
                        [
                            -90.194061,
                            35.17376
                        ],
                        [
                            -90.19397,
                            35.173493
                        ],
                        [
                            -90.193821,
                            35.1731
                        ],
                        [
                            -90.193555,
                            35.172554
                        ],
                        [
                            -90.193303,
                            35.172123
                        ],
                        [
                            -90.193003,
                            35.17173
                        ],
                        [
                            -90.192828,
                            35.171564
                        ],
                        [
                            -90.192537,
                            35.171288
                        ],
                        [
                            -90.192222,
                            35.171028
                        ],
                        [
                            -90.191814,
                            35.170729
                        ],
                        [
                            -90.191396,
                            35.170479
                        ],
                        [
                            -90.190797,
                            35.170151
                        ],
                        [
                            -90.189997,
                            35.169886
                        ],
                        [
                            -90.189689,
                            35.1698
                        ],
                        [
                            -90.189091,
                            35.169672
                        ],
                        [
                            -90.187723,
                            35.169385
                        ],
                        [
                            -90.187349,
                            35.169288
                        ],
                        [
                            -90.186347,
                            35.168972
                        ],
                        [
                            -90.186191,
                            35.168918
                        ],
                        [
                            -90.184188,
                            35.168186
                        ],
                        [
                            -90.183218,
                            35.167778
                        ],
                        [
                            -90.181176,
                            35.166987
                        ],
                        [
                            -90.178971,
                            35.166158
                        ],
                        [
                            -90.176918,
                            35.165352
                        ],
                        [
                            -90.17533,
                            35.164766
                        ],
                        [
                            -90.170638,
                            35.162969
                        ],
                        [
                            -90.16654,
                            35.161375
                        ],
                        [
                            -90.164679,
                            35.160692
                        ],
                        [
                            -90.164629,
                            35.160675
                        ],
                        [
                            -90.164268,
                            35.160537
                        ],
                        [
                            -90.157657,
                            35.157986
                        ],
                        [
                            -90.153177,
                            35.156295
                        ],
                        [
                            -90.152739,
                            35.156125
                        ],
                        [
                            -90.151359,
                            35.155611
                        ],
                        [
                            -90.145402,
                            35.153309
                        ],
                        [
                            -90.143675,
                            35.15266
                        ],
                        [
                            -90.137077,
                            35.150107
                        ],
                        [
                            -90.135049,
                            35.149344
                        ],
                        [
                            -90.133193,
                            35.148563
                        ],
                        [
                            -90.132796,
                            35.148326
                        ],
                        [
                            -90.131841,
                            35.14766
                        ],
                        [
                            -90.13109,
                            35.147203
                        ],
                        [
                            -90.130457,
                            35.146914
                        ],
                        [
                            -90.129846,
                            35.14673
                        ],
                        [
                            -90.129084,
                            35.146607
                        ],
                        [
                            -90.128247,
                            35.146563
                        ],
                        [
                            -90.126402,
                            35.146519
                        ],
                        [
                            -90.125876,
                            35.146458
                        ],
                        [
                            -90.125253,
                            35.146317
                        ],
                        [
                            -90.12399,
                            35.145959
                        ],
                        [
                            -90.120836,
                            35.145076
                        ],
                        [
                            -90.109859,
                            35.141955
                        ],
                        [
                            -90.104161,
                            35.140308
                        ],
                        [
                            -90.098614,
                            35.138729
                        ],
                        [
                            -90.096211,
                            35.138062
                        ],
                        [
                            -90.095788,
                            35.13794
                        ],
                        [
                            -90.092794,
                            35.137082
                        ],
                        [
                            -90.088466,
                            35.135859
                        ],
                        [
                            -90.087843,
                            35.13565
                        ],
                        [
                            -90.087232,
                            35.135425
                        ],
                        [
                            -90.086385,
                            35.135073
                        ],
                        [
                            -90.085769,
                            35.134794
                        ],
                        [
                            -90.085204,
                            35.134506
                        ],
                        [
                            -90.084658,
                            35.134203
                        ],
                        [
                            -90.084188,
                            35.133929
                        ],
                        [
                            -90.083238,
                            35.133301
                        ],
                        [
                            -90.082311,
                            35.132602
                        ],
                        [
                            -90.076117,
                            35.127742
                        ],
                        [
                            -90.073353,
                            35.125573
                        ],
                        [
                            -90.072978,
                            35.125284
                        ],
                        [
                            -90.072685,
                            35.125083
                        ],
                        [
                            -90.072433,
                            35.124969
                        ],
                        [
                            -90.07213,
                            35.124859
                        ],
                        [
                            -90.071749,
                            35.124774
                        ],
                        [
                            -90.071465,
                            35.124747
                        ],
                        [
                            -90.071213,
                            35.124742
                        ],
                        [
                            -90.070156,
                            35.124757
                        ],
                        [
                            -90.069443,
                            35.124658
                        ],
                        [
                            -90.069144,
                            35.12455
                        ],
                        [
                            -90.068719,
                            35.124317
                        ],
                        [
                            -90.068333,
                            35.124013
                        ],
                        [
                            -90.068114,
                            35.12378
                        ],
                        [
                            -90.067954,
                            35.123541
                        ],
                        [
                            -90.067863,
                            35.123326
                        ],
                        [
                            -90.067799,
                            35.123055
                        ],
                        [
                            -90.067746,
                            35.122643
                        ],
                        [
                            -90.067763,
                            35.122402
                        ],
                        [
                            -90.067826,
                            35.12216
                        ],
                        [
                            -90.067881,
                            35.122002
                        ],
                        [
                            -90.067989,
                            35.121776
                        ],
                        [
                            -90.068309,
                            35.12135
                        ],
                        [
                            -90.069162,
                            35.120584
                        ],
                        [
                            -90.069601,
                            35.120127
                        ],
                        [
                            -90.069753,
                            35.119945
                        ],
                        [
                            -90.070238,
                            35.119258
                        ],
                        [
                            -90.07039,
                            35.119039
                        ],
                        [
                            -90.070743,
                            35.118454
                        ],
                        [
                            -90.071653,
                            35.11708
                        ],
                        [
                            -90.07219,
                            35.116282
                        ],
                        [
                            -90.073169,
                            35.114861
                        ],
                        [
                            -90.073703,
                            35.114088
                        ],
                        [
                            -90.074336,
                            35.113105
                        ],
                        [
                            -90.074657,
                            35.112561
                        ],
                        [
                            -90.07484,
                            35.111999
                        ],
                        [
                            -90.075649,
                            35.108138
                        ],
                        [
                            -90.075747,
                            35.10768
                        ],
                        [
                            -90.076108,
                            35.105621
                        ],
                        [
                            -90.07619,
                            35.104896
                        ],
                        [
                            -90.076782,
                            35.091781
                        ],
                        [
                            -90.07687,
                            35.090267
                        ],
                        [
                            -90.076886,
                            35.090007
                        ],
                        [
                            -90.077009,
                            35.089238
                        ],
                        [
                            -90.077288,
                            35.088298
                        ],
                        [
                            -90.07712,
                            35.087735
                        ],
                        [
                            -90.076718,
                            35.087293
                        ],
                        [
                            -90.076913,
                            35.086999
                        ],
                        [
                            -90.07695,
                            35.086829
                        ],
                        [
                            -90.076679,
                            35.086276
                        ],
                        [
                            -90.076416,
                            35.085882
                        ],
                        [
                            -90.075974,
                            35.085284
                        ],
                        [
                            -90.075504,
                            35.084602
                        ],
                        [
                            -90.075381,
                            35.084406
                        ],
                        [
                            -90.07496,
                            35.083683
                        ],
                        [
                            -90.07403,
                            35.08221
                        ],
                        [
                            -90.07348,
                            35.081595
                        ],
                        [
                            -90.072964,
                            35.081116
                        ],
                        [
                            -90.07249,
                            35.080752
                        ],
                        [
                            -90.07232,
                            35.080622
                        ],
                        [
                            -90.071693,
                            35.080265
                        ],
                        [
                            -90.071065,
                            35.080023
                        ],
                        [
                            -90.070023,
                            35.079704
                        ],
                        [
                            -90.069497,
                            35.079599
                        ],
                        [
                            -90.068639,
                            35.079493
                        ],
                        [
                            -90.06778,
                            35.079458
                        ],
                        [
                            -90.066868,
                            35.079519
                        ],
                        [
                            -90.065526,
                            35.0797
                        ],
                        [
                            -90.062019,
                            35.080169
                        ],
                        [
                            -90.06101,
                            35.080196
                        ],
                        [
                            -90.059938,
                            35.080073
                        ],
                        [
                            -90.059036,
                            35.079888
                        ],
                        [
                            -90.058296,
                            35.079678
                        ],
                        [
                            -90.05751,
                            35.079376
                        ],
                        [
                            -90.05571,
                            35.078685
                        ],
                        [
                            -90.054755,
                            35.078422
                        ],
                        [
                            -90.053726,
                            35.078238
                        ],
                        [
                            -90.053045,
                            35.078171
                        ],
                        [
                            -90.051203,
                            35.078012
                        ],
                        [
                            -90.050394,
                            35.077939
                        ],
                        [
                            -90.049448,
                            35.077827
                        ],
                        [
                            -90.048934,
                            35.077751
                        ],
                        [
                            -90.048128,
                            35.077604
                        ],
                        [
                            -90.047468,
                            35.077462
                        ],
                        [
                            -90.046711,
                            35.077273
                        ],
                        [
                            -90.045086,
                            35.076797
                        ],
                        [
                            -90.043455,
                            35.076311
                        ],
                        [
                            -90.042861,
                            35.076131
                        ],
                        [
                            -90.04254,
                            35.076039
                        ],
                        [
                            -90.041611,
                            35.075766
                        ],
                        [
                            -90.04023,
                            35.075392
                        ],
                        [
                            -90.040022,
                            35.075344
                        ],
                        [
                            -90.032115,
                            35.073604
                        ],
                        [
                            -90.031484,
                            35.073397
                        ],
                        [
                            -90.030747,
                            35.073228
                        ],
                        [
                            -90.030455,
                            35.073138
                        ],
                        [
                            -90.029929,
                            35.072899
                        ],
                        [
                            -90.029481,
                            35.072627
                        ],
                        [
                            -90.029244,
                            35.072433
                        ],
                        [
                            -90.029026,
                            35.072254
                        ],
                        [
                            -90.028708,
                            35.071854
                        ],
                        [
                            -90.028382,
                            35.071292
                        ],
                        [
                            -90.028211,
                            35.070688
                        ],
                        [
                            -90.028008,
                            35.069826
                        ],
                        [
                            -90.027636,
                            35.068508
                        ],
                        [
                            -90.027497,
                            35.068148
                        ],
                        [
                            -90.027288,
                            35.067683
                        ],
                        [
                            -90.02691,
                            35.066959
                        ],
                        [
                            -90.026579,
                            35.066447
                        ],
                        [
                            -90.026323,
                            35.066095
                        ],
                        [
                            -90.025968,
                            35.06565
                        ],
                        [
                            -90.025618,
                            35.065273
                        ],
                        [
                            -90.024869,
                            35.064542
                        ],
                        [
                            -90.024165,
                            35.063946
                        ],
                        [
                            -90.023494,
                            35.063458
                        ],
                        [
                            -90.022886,
                            35.063063
                        ],
                        [
                            -90.022189,
                            35.062659
                        ],
                        [
                            -90.020491,
                            35.06172
                        ],
                        [
                            -90.020003,
                            35.061438
                        ],
                        [
                            -90.019544,
                            35.061185
                        ],
                        [
                            -90.018994,
                            35.06086
                        ],
                        [
                            -90.018294,
                            35.060385
                        ],
                        [
                            -90.017682,
                            35.059873
                        ],
                        [
                            -90.017432,
                            35.05964
                        ],
                        [
                            -90.017114,
                            35.05931
                        ],
                        [
                            -90.016823,
                            35.058972
                        ],
                        [
                            -90.016593,
                            35.058675
                        ],
                        [
                            -90.015101,
                            35.056483
                        ],
                        [
                            -90.012018,
                            35.051926
                        ],
                        [
                            -90.011287,
                            35.050815
                        ],
                        [
                            -90.007952,
                            35.045936
                        ],
                        [
                            -90.00726,
                            35.044967
                        ],
                        [
                            -90.004813,
                            35.041312
                        ],
                        [
                            -90.003854,
                            35.039549
                        ],
                        [
                            -90.003438,
                            35.038543
                        ],
                        [
                            -90.003163,
                            35.037757
                        ],
                        [
                            -90.002818,
                            35.036517
                        ],
                        [
                            -90.002695,
                            35.035751
                        ],
                        [
                            -90.002619,
                            35.035127
                        ],
                        [
                            -90.002596,
                            35.03141
                        ],
                        [
                            -90.002597,
                            35.030845
                        ],
                        [
                            -90.002642,
                            35.025799
                        ],
                        [
                            -90.002637,
                            35.024689
                        ],
                        [
                            -90.002686,
                            35.021633
                        ],
                        [
                            -90.002702,
                            35.020858
                        ],
                        [
                            -90.002728,
                            35.017599
                        ],
                        [
                            -90.002667,
                            35.01402
                        ],
                        [
                            -90.002667,
                            35.013515
                        ],
                        [
                            -90.002787,
                            35.003367
                        ],
                        [
                            -90.002777,
                            35.002572
                        ],
                        [
                            -90.002706,
                            35.00111
                        ],
                        [
                            -90.002661,
                            35.000163
                        ],
                        [
                            -90.00263,
                            34.998303
                        ],
                        [
                            -90.002584,
                            34.996485
                        ],
                        [
                            -90.002549,
                            34.994965
                        ],
                        [
                            -90.002455,
                            34.99241
                        ],
                        [
                            -90.002423,
                            34.991483
                        ],
                        [
                            -90.002337,
                            34.989817
                        ],
                        [
                            -90.002217,
                            34.985472
                        ],
                        [
                            -90.002165,
                            34.983186
                        ],
                        [
                            -90.001993,
                            34.980303
                        ],
                        [
                            -90.001768,
                            34.977776
                        ],
                        [
                            -90.001668,
                            34.976893
                        ],
                        [
                            -90.001534,
                            34.975797
                        ],
                        [
                            -90.001277,
                            34.973985
                        ],
                        [
                            -90.000919,
                            34.971672
                        ],
                        [
                            -90.000317,
                            34.968013
                        ],
                        [
                            -90.00028,
                            34.967288
                        ],
                        [
                            -90.000185,
                            34.966106
                        ],
                        [
                            -90.000197,
                            34.965719
                        ],
                        [
                            -90.0003,
                            34.965144
                        ],
                        [
                            -90.000363,
                            34.964916
                        ],
                        [
                            -90.000587,
                            34.964352
                        ],
                        [
                            -90.000795,
                            34.963734
                        ],
                        [
                            -90.00084,
                            34.963449
                        ],
                        [
                            -90.000837,
                            34.963275
                        ],
                        [
                            -90.000949,
                            34.96318
                        ],
                        [
                            -90.001036,
                            34.963026
                        ],
                        [
                            -90.001188,
                            34.962875
                        ],
                        [
                            -90.001376,
                            34.9628
                        ],
                        [
                            -90.001507,
                            34.962768
                        ],
                        [
                            -90.001861,
                            34.962727
                        ],
                        [
                            -90.003965,
                            34.962763
                        ],
                        [
                            -90.003965,
                            34.962626
                        ],
                        [
                            -90.003958,
                            34.962126
                        ],
                        [
                            -90.003952,
                            34.96198
                        ],
                        [
                            -90.003943,
                            34.961809
                        ],
                        [
                            -90.003918,
                            34.960984
                        ],
                        [
                            -90.003917,
                            34.960966
                        ],
                        [
                            -90.003903,
                            34.960646
                        ],
                        [
                            -90.003899,
                            34.960547
                        ],
                        [
                            -90.003876,
                            34.960072
                        ],
                        [
                            -90.003897,
                            34.95992
                        ],
                        [
                            -90.003906,
                            34.959751
                        ],
                        [
                            -90.004008,
                            34.959703
                        ],
                        [
                            -90.004109,
                            34.959052
                        ],
                        [
                            -90.004236,
                            34.958428
                        ],
                        [
                            -90.004365,
                            34.958014
                        ],
                        [
                            -90.004414,
                            34.957882
                        ],
                        [
                            -90.004624,
                            34.957468
                        ],
                        [
                            -90.004868,
                            34.95709
                        ],
                        [
                            -90.005695,
                            34.955973
                        ],
                        [
                            -90.006004,
                            34.955562
                        ],
                        [
                            -90.006127,
                            34.955297
                        ],
                        [
                            -90.006229,
                            34.954943
                        ],
                        [
                            -90.006251,
                            34.954759
                        ],
                        [
                            -90.006251,
                            34.953756
                        ],
                        [
                            -90.006248,
                            34.952343
                        ],
                        [
                            -90.006244,
                            34.951032
                        ],
                        [
                            -90.006226,
                            34.950787
                        ],
                        [
                            -90.006155,
                            34.950276
                        ],
                        [
                            -90.005973,
                            34.949686
                        ],
                        [
                            -90.007104,
                            34.949396
                        ],
                        [
                            -90.00793,
                            34.949228
                        ],
                        [
                            -90.008161,
                            34.949198
                        ],
                        [
                            -90.008253,
                            34.949186
                        ],
                        [
                            -90.008977,
                            34.949175
                        ],
                        [
                            -90.009877,
                            34.949186
                        ],
                        [
                            -90.011539,
                            34.949186
                        ],
                        [
                            -90.012613,
                            34.949178
                        ],
                        [
                            -90.012869,
                            34.949158
                        ],
                        [
                            -90.013383,
                            34.949083
                        ],
                        [
                            -90.013812,
                            34.948981
                        ],
                        [
                            -90.01498,
                            34.948587
                        ],
                        [
                            -90.015216,
                            34.948504
                        ],
                        [
                            -90.015581,
                            34.948411
                        ],
                        [
                            -90.016223,
                            34.948352
                        ],
                        [
                            -90.016505,
                            34.948272
                        ],
                        [
                            -90.016849,
                            34.948221
                        ],
                        [
                            -90.017306,
                            34.948211
                        ],
                        [
                            -90.017398,
                            34.94821
                        ],
                        [
                            -90.018476,
                            34.948184
                        ],
                        [
                            -90.019123,
                            34.948165
                        ],
                        [
                            -90.020766,
                            34.948148
                        ],
                        [
                            -90.02101,
                            34.948144
                        ],
                        [
                            -90.021151,
                            34.948141
                        ],
                        [
                            -90.021825,
                            34.948126
                        ],
                        [
                            -90.02245,
                            34.948114
                        ],
                        [
                            -90.024566,
                            34.948089
                        ],
                        [
                            -90.025623,
                            34.948077
                        ],
                        [
                            -90.028414,
                            34.948085
                        ],
                        [
                            -90.031552,
                            34.948092
                        ],
                        [
                            -90.033606,
                            34.94808
                        ],
                        [
                            -90.034201,
                            34.948078
                        ],
                        [
                            -90.034245,
                            34.94843
                        ],
                        [
                            -90.034241,
                            34.948766
                        ],
                        [
                            -90.034236,
                            34.949418
                        ],
                        [
                            -90.034245,
                            34.95023
                        ],
                        [
                            -90.034249,
                            34.950667
                        ],
                        [
                            -90.033873,
                            34.950693
                        ],
                        [
                            -90.03207,
                            34.950723
                        ],
                        [
                            -90.032083,
                            34.951598
                        ],
                        [
                            -90.031613,
                            34.951592
                        ]
                    ],
                    "type": "LineString"
                }
            }
        ]
    }
}