{
    "road_distance_raw": {
        "features": [
            {
                "properties": {
                    "summary": {
                        "distance": 40264.8,
                        "duration": 2621.2
                    }
                },
                "geometry": {
                    "coordinates": [
                        [
                            -87.745929,
                            41.77032
                        ],
                        [
                            -87.745957,
                            41.771074
                        ],
                        [
                            -87.745745,
                            41.771077
                        ],
                        [
                            -87.745073,
                            41.771088
                        ],
                        [
                            -87.744307,
                            41.7711
                        ],
                        [
                            -87.744101,
                            41.771104
                        ],
                        [
                            -87.743261,
                            41.771117
                        ],
                        [
                            -87.743005,
                            41.771122
                        ],
                        [
                            -87.74272,
                            41.771126
                        ],
                        [
                            -87.742488,
                            41.771077
                        ],
                        [
                            -87.742387,
                            41.771029
                        ],
                        [
                            -87.742141,
                            41.770848
                        ],
                        [
                            -87.742103,
                            41.769957
                        ],
                        [
                            -87.742124,
                            41.769659
                        ],
                        [
                            -87.742124,
                            41.768754
                        ],
                        [
                            -87.742086,
                            41.767022
                        ],
                        [
                            -87.741986,
                            41.765233
                        ],
                        [
                            -87.741952,
                            41.764895
                        ],
                        [
                            -87.741893,
                            41.764298
                        ],
                        [
                            -87.741881,
                            41.764008
                        ],
                        [
                            -87.741864,
                            41.763608
                        ],
                        [
                            -87.741861,
                            41.763536
                        ],
                        [
                            -87.741848,
                            41.763175
                        ],
                        [
                            -87.741834,
                            41.762814
                        ],
                        [
                            -87.741816,
                            41.762329
                        ],
                        [
                            -87.741801,
                            41.761921
                        ],
                        [
                            -87.741784,
                            41.761333
                        ],
                        [
                            -87.741778,
                            41.761149
                        ],
                        [
                            -87.741771,
                            41.760902
                        ],
                        [
                            -87.741767,
                            41.760757
                        ],
                        [
                            -87.74175,
                            41.760184
                        ],
                        [
                            -87.741749,
                            41.760147
                        ],
                        [
                            -87.741724,
                            41.759696
                        ],
                        [
                            -87.741717,
                            41.759567
                        ],
                        [
                            -87.742424,
                            41.75909
                        ],
                        [
                            -87.742821,
                            41.758825
                        ],
                        [
                            -87.743306,
                            41.758503
                        ],
                        [
                            -87.744305,
                            41.757831
                        ],
                        [
                            -87.745177,
                            41.757245
                        ],
                        [
                            -87.745209,
                            41.757223
                        ],
                        [
                            -87.745964,
                            41.756716
                        ],
                        [
                            -87.746432,
                            41.756403
                        ],
                        [
                            -87.746977,
                            41.756037
                        ],
                        [
                            -87.748242,
                            41.755192
                        ],
                        [
                            -87.749236,
                            41.754526
                        ],
                        [
                            -87.750024,
                            41.75397
                        ],
                        [
                            -87.751196,
                            41.75319
                        ],
                        [
                            -87.752395,
                            41.752377
                        ],
                        [
                            -87.753579,
                            41.751568
                        ],
                        [
                            -87.754778,
                            41.750791
                        ],
                        [
                            -87.755915,
                            41.750026
                        ],
                        [
                            -87.756711,
                            41.749486
                        ],
                        [
                            -87.756855,
                            41.74939
                        ],
                        [
                            -87.756946,
                            41.749374
                        ],
                        [
                            -87.757168,
                            41.74923
                        ],
                        [
                            -87.757233,
                            41.749185
                        ],
                        [
                            -87.757382,
                            41.749081
                        ],
                        [
                            -87.757445,
                            41.749037
                        ],
                        [
                            -87.757438,
                            41.748984
                        ],
                        [
                            -87.757521,
                            41.748919
                        ],
                        [
                            -87.7577,
                            41.748801
                        ],
                        [
                            -87.757961,
                            41.748628
                        ],
                        [
                            -87.758074,
                            41.748553
                        ],
                        [
                            -87.758374,
                            41.748355
                        ],
                        [
                            -87.75862,
                            41.748186
                        ],
                        [
                            -87.758784,
                            41.748067
                        ],
                        [
                            -87.75893,
                            41.74797
                        ],
                        [
                            -87.759272,
                            41.74774
                        ],
                        [
                            -87.759469,
                            41.747608
                        ],
                        [
                            -87.759476,
                            41.747604
                        ],
                        [
                            -87.760096,
                            41.747187
                        ],
                        [
                            -87.760738,
                            41.746757
                        ],
                        [
                            -87.761895,
                            41.745971
                        ],
                        [
                            -87.761941,
                            41.745941
                        ],
                        [
                            -87.763045,
                            41.745192
                        ],
                        [
                            -87.763066,
                            41.745177
                        ],
                        [
                            -87.763298,
                            41.745027
                        ],
                        [
                            -87.764649,
                            41.74413
                        ],
                        [
                            -87.766028,
                            41.743201
                        ],
                        [
                            -87.767273,
                            41.742362
                        ],
                        [
                            -87.768175,
                            41.74175
                        ],
                        [
                            -87.768759,
                            41.741352
                        ],
                        [
                            -87.769706,
                            41.740716
                        ],
                        [
                            -87.770206,
                            41.740384
                        ],
                        [
                            -87.772901,
                            41.738549
                        ],
                        [
                            -87.773035,
                            41.738459
                        ],
                        [
                            -87.77376,
                            41.737996
                        ],
                        [
                            -87.7743,
                            41.737597
                        ],
                        [
                            -87.774957,
                            41.737167
                        ],
                        [
                            -87.777405,
                            41.735523
                        ],
                        [
                            -87.778549,
                            41.734749
                        ],
                        [
                            -87.778959,
                            41.734483
                        ],
                        [
                            -87.779096,
                            41.734451
                        ],
                        [
                            -87.779687,
                            41.734043
                        ],
                        [
                            -87.779904,
                            41.733902
                        ],
                        [
                            -87.780207,
                            41.733901
                        ],
                        [
                            -87.780418,
                            41.733899
                        ],
                        [
                            -87.780685,
                            41.733894
                        ],
                        [
                            -87.780896,
                            41.733891
                        ],
                        [
                            -87.782113,
                            41.733872
                        ],
                        [
                            -87.782453,
                            41.733866
                        ],
                        [
                            -87.782903,
                            41.733859
                        ],
                        [
                            -87.783991,
                            41.73384
                        ],
                        [
                            -87.784519,
                            41.733827
                        ],
                        [
                            -87.785204,
                            41.733815
                        ],
                        [
                            -87.78627,
                            41.733794
                        ],
                        [
                            -87.786517,
                            41.733789
                        ],
                        [
                            -87.786966,
                            41.733779
                        ],
                        [
                            -87.787477,
                            41.733776
                        ],
                        [
                            -87.788243,
                            41.733762
                        ],
                        [
                            -87.789396,
                            41.73374
                        ],
                        [
                            -87.789725,
                            41.733733
                        ],
                        [
                            -87.789889,
                            41.73373
                        ],
                        [
                            -87.790121,
                            41.733725
                        ],
                        [
                            -87.790609,
                            41.733716
                        ],
                        [
                            -87.791125,
                            41.733706
                        ],
                        [
                            -87.791423,
                            41.733701
                        ],
                        [
                            -87.791462,
                            41.7337
                        ],
                        [
                            -87.79163,
                            41.733697
                        ],
                        [
                            -87.791827,
                            41.733693
                        ],
                        [
                            -87.792718,
                            41.733681
                        ],
                        [
                            -87.793045,
                            41.733676
                        ],
                        [
                            -87.793982,
                            41.733656
                        ],
                        [
                            -87.794249,
                            41.73365
                        ],
                        [
                            -87.795171,
                            41.733631
                        ],
                        [
                            -87.79574,
                            41.733619
                        ],
                        [
                            -87.796662,
                            41.733599
                        ],
                        [
                            -87.796987,
                            41.733592
                        ],
                        [
                            -87.797535,
                            41.733578
                        ],
                        [
                            -87.798261,
                            41.73356
                        ],
                        [
                            -87.79838,
                            41.733557
                        ],
                        [
                            -87.798748,
                            41.73355
                        ],
                        [
                            -87.798936,
                            41.733539
                        ],
                        [
                            -87.799064,
                            41.733505
                        ],
                        [
                            -87.79921,
                            41.733502
                        ],
                        [
                            -87.799195,
                            41.733113
                        ],
                        [
                            -87.799182,
                            41.732776
                        ],
                        [
                            -87.799177,
                            41.732635
                        ],
                        [
                            -87.799147,
                            41.731879
                        ],
                        [
                            -87.799137,
                            41.731622
                        ],
                        [
                            -87.799134,
                            41.731555
                        ],
                        [
                            -87.799114,
                            41.731028
                        ],
                        [
                            -87.79907,
                            41.730406
                        ],
                        [
                            -87.799057,
                            41.730181
                        ],
                        [
                            -87.799035,
                            41.729775
                        ],
                        [
                            -87.799025,
                            41.729597
                        ],
                        [
                            -87.799023,
                            41.729429
                        ],
                        [
                            -87.799021,
                            41.729346
                        ],
                        [
                            -87.799018,
                            41.729214
                        ],
                        [
                            -87.799016,
                            41.72909
                        ],
                        [
                            -87.799009,
                            41.728819
                        ],
                        [
                            -87.79901,
                            41.728799
                        ],
                        [
                            -87.799018,
                            41.728565
                        ],
                        [
                            -87.799012,
                            41.728426
                        ],
                        [
                            -87.799011,
                            41.7284
                        ],
                        [
                            -87.799004,
                            41.728219
                        ],
                        [
                            -87.798997,
                            41.728024
                        ],
                        [
                            -87.798965,
                            41.727653
                        ],
                        [
                            -87.798955,
                            41.72744
                        ],
                        [
                            -87.798943,
                            41.727167
                        ],
                        [
                            -87.798929,
                            41.726913
                        ],
                        [
                            -87.798911,
                            41.726539
                        ],
                        [
                            -87.798906,
                            41.72632
                        ],
                        [
                            -87.798884,
                            41.725712
                        ],
                        [
                            -87.798871,
                            41.725353
                        ],
                        [
                            -87.798846,
                            41.724386
                        ],
                        [
                            -87.798833,
                            41.723838
                        ],
                        [
                            -87.798819,
                            41.723487
                        ],
                        [
                            -87.798749,
                            41.721663
                        ],
                        [
                            -87.798848,
                            41.721134
                        ],
                        [
                            -87.798892,
                            41.721019
                        ],
                        [
                            -87.79896,
                            41.720913
                        ],
                        [
                            -87.799043,
                            41.720819
                        ],
                        [
                            -87.799245,
                            41.720693
                        ],
                        [
                            -87.800016,
                            41.720414
                        ],
                        [
                            -87.800198,
                            41.720315
                        ],
                        [
                            -87.800281,
                            41.720246
                        ],
                        [
                            -87.80042,
                            41.720064
                        ],
                        [
                            -87.800662,
                            41.719459
                        ],
                        [
                            -87.800826,
                            41.71928
                        ],
                        [
                            -87.801033,
                            41.719161
                        ],
                        [
                            -87.801324,
                            41.719077
                        ],
                        [
                            -87.802353,
                            41.718921
                        ],
                        [
                            -87.80424,
                            41.718862
                        ],
                        [
                            -87.804545,
                            41.718856
                        ],
                        [
                            -87.807783,
                            41.718808
                        ],
                        [
                            -87.808729,
                            41.718798
                        ],
                        [
                            -87.809177,
                            41.718791
                        ],
                        [
                            -87.80945,
                            41.718721
                        ],
                        [
                            -87.809427,
                            41.718302
                        ],
                        [
                            -87.809405,
                            41.718205
                        ],
                        [
                            -87.809367,
                            41.718104
                        ],
                        [
                            -87.809331,
                            41.718046
                        ],
                        [
                            -87.809321,
                            41.717957
                        ],
                        [
                            -87.809043,
                            41.717681
                        ],
                        [
                            -87.808979,
                            41.717592
                        ],
                        [
                            -87.80892,
                            41.71762
                        ],
                        [
                            -87.808751,
                            41.717569
                        ],
                        [
                            -87.808401,
                            41.717536
                        ],
                        [
                            -87.807519,
                            41.717348
                        ],
                        [
                            -87.807087,
                            41.717236
                        ],
                        [
                            -87.806644,
                            41.7171
                        ],
                        [
                            -87.806244,
                            41.716943
                        ],
                        [
                            -87.80597,
                            41.716815
                        ],
                        [
                            -87.805711,
                            41.716683
                        ],
                        [
                            -87.805241,
                            41.716356
                        ],
                        [
                            -87.801417,
                            41.713357
                        ],
                        [
                            -87.800775,
                            41.712947
                        ],
                        [
                            -87.798717,
                            41.711276
                        ],
                        [
                            -87.797983,
                            41.710678
                        ],
                        [
                            -87.791698,
                            41.705604
                        ],
                        [
                            -87.789918,
                            41.704135
                        ],
                        [
                            -87.789793,
                            41.704032
                        ],
                        [
                            -87.78916,
                            41.703523
                        ],
                        [
                            -87.788988,
                            41.703386
                        ],
                        [
                            -87.788471,
                            41.702971
                        ],
                        [
                            -87.78787,
                            41.7024
                        ],
                        [
                            -87.787364,
                            41.701779
                        ],
                        [
                            -87.786963,
                            41.701187
                        ],
                        [
                            -87.786748,
                            41.700808
                        ],
                        [
                            -87.78646,
                            41.700192
                        ],
                        [
                            -87.786207,
                            41.69935
                        ],
                        [
                            -87.785985,
                            41.698541
                        ],
                        [
                            -87.785715,
                            41.697635
                        ],
                        [
                            -87.785664,
                            41.697456
                        ],
                        [
                            -87.78521,
                            41.69578
                        ],
                        [
                            -87.784497,
                            41.693274
                        ],
                        [
                            -87.784094,
                            41.692242
                        ],
                        [
                            -87.783212,
                            41.690399
                        ],
                        [
                            -87.783125,
                            41.690215
                        ],
                        [
                            -87.782308,
                            41.688551
                        ],
                        [
                            -87.781455,
                            41.686754
                        ],
                        [
                            -87.780255,
                            41.684219
                        ],
                        [
                            -87.779904,
                            41.68361
                        ],
                        [
                            -87.779486,
                            41.683058
                        ],
                        [
                            -87.779331,
                            41.682878
                        ],
                        [
                            -87.778697,
                            41.682218
                        ],
                        [
                            -87.778386,
                            41.681908
                        ],
                        [
                            -87.77527,
                            41.678929
                        ],
                        [
                            -87.772781,
                            41.676576
                        ],
                        [
                            -87.772189,
                            41.676089
                        ],
                        [
                            -87.771399,
                            41.675512
                        ],
                        [
                            -87.770481,
                            41.675012
                        ],
                        [
                            -87.764233,
                            41.672025
                        ],
                        [
                            -87.758877,
                            41.669441
                        ],
                        [
                            -87.754695,
                            41.667379
                        ],
                        [
                            -87.752758,
                            41.666445
                        ],
                        [
                            -87.752046,
                            41.666137
                        ],
                        [
                            -87.750945,
                            41.665738
                        ],
                        [
                            -87.749299,
                            41.66536
                        ],
                        [
                            -87.747859,
                            41.665135
                        ],
                        [
                            -87.745123,
                            41.664762
                        ],
                        [
                            -87.743446,
                            41.664514
                        ],
                        [
                            -87.7425,
                            41.664329
                        ],
                        [
                            -87.741518,
                            41.664084
                        ],
                        [
                            -87.740414,
                            41.663677
                        ],
                        [
                            -87.735737,
                            41.661278
                        ],
                        [
                            -87.731068,
                            41.65881
                        ],
                        [
                            -87.7299,
                            41.658079
                        ],
                        [
                            -87.729136,
                            41.657476
                        ],
                        [
                            -87.728415,
                            41.656822
                        ],
                        [
                            -87.728283,
                            41.656669
                        ],
                        [
                            -87.727857,
                            41.656264
                        ],
                        [
                            -87.727394,
                            41.655687
                        ],
                        [
                            -87.726827,
                            41.65484
                        ],
                        [
                            -87.726639,
                            41.654491
                        ],
                        [
                            -87.725725,
                            41.652658
                        ],
                        [
                            -87.724747,
                            41.650716
                        ],
                        [
                            -87.723177,
                            41.647595
                        ],
                        [
                            -87.723008,
                            41.647253
                        ],
                        [
                            -87.722624,
                            41.646508
                        ],
                        [
                            -87.720161,
                            41.641509
                        ],
                        [
                            -87.720033,
                            41.641256
                        ],
                        [
                            -87.719549,
                            41.640358
                        ],
                        [
                            -87.719154,
                            41.639704
                        ],
                        [
                            -87.718414,
                            41.638779
                        ],
                        [
                            -87.7181,
                            41.638384
                        ],
                        [
                            -87.717755,
                            41.637972
                        ],
                        [
                            -87.717094,
                            41.637253
                        ],
                        [
                            -87.716365,
                            41.636567
                        ],
                        [
                            -87.715446,
                            41.635797
                        ],
                        [
                            -87.714605,
                            41.635201
                        ],
                        [
                            -87.713756,
                            41.63463
                        ],
                        [
                            -87.712586,
                            41.633974
                        ],
                        [
                            -87.712366,
                            41.633873
                        ],
                        [
                            -87.711271,
                            41.633411
                        ],
                        [
                            -87.710144,
                            41.633075
                        ],
                        [
                            -87.709097,
                            41.632856
                        ],
                        [
                            -87.708101,
                            41.632739
                        ],
                        [
                            -87.706969,
                            41.632671
                        ],
                        [
                            -87.705018,
                            41.632709
                        ],
                        [
                            -87.703947,
                            41.63273
                        ],
                        [
                            -87.702768,
                            41.632761
                        ],
                        [
                            -87.701711,
                            41.632757
                        ],
                        [
                            -87.700732,
                            41.63267
                        ],
                        [
                            -87.699752,
                            41.632517
                        ],
                        [
                            -87.698824,
                            41.6323
                        ],
                        [
                            -87.698323,
                            41.63216
                        ],
                        [
                            -87.697248,
                            41.63176
                        ],
                        [
                            -87.696024,
                            41.631166
                        ],
                        [
                            -87.695242,
                            41.630729
                        ],
                        [
                            -87.694572,
                            41.630216
                        ],
                        [
                            -87.6938,
                            41.629504
                        ],
                        [
                            -87.693302,
                            41.628888
                        ],
                        [
                            -87.692839,
                            41.628182
                        ],
                        [
                            -87.691783,
                            41.626282
                        ],
                        [
                            -87.691517,
                            41.625823
                        ],
                        [
                            -87.690749,
                            41.624358
                        ],
                        [
                            -87.690586,
                            41.623843
                        ],
                        [
                            -87.689665,
                            41.62202
                        ],
                        [
                            -87.688533,
                            41.619658
                        ],
                        [
                            -87.688418,
                            41.619348
                        ],
                        [
                            -87.68836,
                            41.619035
                        ],
                        [
                            -87.688358,
                            41.618724
                        ],
                        [
                            -87.688381,
                            41.618567
                        ],
                        [
                            -87.688416,
                            41.618413
                        ],
                        [
                            -87.688529,
                            41.618101
                        ],
                        [
                            -87.688609,
                            41.617952
                        ],
                        [
                            -87.688802,
                            41.617672
                        ],
                        [
                            -87.689175,
                            41.617292
                        ],
                        [
                            -87.694006,
                            41.613549
                        ],
                        [
                            -87.696202,
                            41.611779
                        ],
                        [
                            -87.697884,
                            41.610349
                        ],
                        [
                            -87.702211,
                            41.607087
                        ],
                        [
                            -87.708573,
                            41.602239
                        ],
                        [
                            -87.709922,
                            41.601065
                        ],
                        [
                            -87.711881,
                            41.599564
                        ],
                        [
                            -87.714461,
                            41.597758
                        ],
                        [
                            -87.714782,
                            41.597499
                        ],
                        [
                            -87.716039,
                            41.596483
                        ],
                        [
                            -87.721292,
                            41.592477
                        ],
                        [
                            -87.724239,
                            41.590259
                        ],
                        [
                            -87.734373,
                            41.582523
                        ],
                        [
                            -87.73548,
                            41.581686
                        ],
                        [
                            -87.737355,
                            41.580225
                        ],
                        [
                            -87.738588,
                            41.579239
                        ],
                        [
                            -87.739769,
                            41.578061
                        ],
                        [
                            -87.740721,
                            41.57694
                        ],
                        [
                            -87.74119,
                            41.576302
                        ],
                        [
                            -87.741733,
                            41.575434
                        ],
                        [
                            -87.742078,
                            41.574804
                        ],
                        [
                            -87.742262,
                            41.574428
                        ],
                        [
                            -87.742816,
                            41.57311
                        ],
                        [
                            -87.743447,
                            41.571139
                        ],
                        [
                            -87.743713,
                            41.570233
                        ],
                        [
                            -87.74435,
                            41.5684
                        ],
                        [
                            -87.744693,
                            41.567353
                        ],
                        [
                            -87.744908,
                            41.566903
                        ],
                        [
                            -87.7452,
                            41.566409
                        ],
                        [
                            -87.745577,
                            41.565953
                        ],
                        [
                            -87.746135,
                            41.56533
                        ],
                        [
                            -87.746727,
                            41.564835
                        ],
                        [
                            -87.747232,
                            41.564364
                        ],
                        [
                            -87.748691,
                            41.563587
                        ],
                        [
                            -87.74981,
                            41.563044
                        ],
                        [
                            -87.755176,
                            41.560634
                        ],
                        [
                            -87.757611,
                            41.559532
                        ],
                        [
                            -87.759785,
                            41.558547
                        ],
                        [
                            -87.765424,
                            41.556042
                        ],
                        [
                            -87.771437,
                            41.553321
                        ],
                        [
                            -87.772973,
                            41.552727
                        ],
                        [
                            -87.774473,
                            41.552248
                        ],
                        [
                            -87.776033,
                            41.551866
                        ],
                        [
                            -87.777595,
                            41.551578
                        ],
                        [
                            -87.778684,
                            41.551425
                        ],
                        [
                            -87.779887,
                            41.55133
                        ],
                        [
                            -87.780971,
                            41.551272
                        ],
                        [
                            -87.78234,
                            41.551247
                        ],
                        [
                            -87.786896,
                            41.551212
                        ],
                        [
                            -87.78747,
                            41.551304
                        ],
                        [
                            -87.787889,
                            41.551354
                        ],
                        [
                            -87.788254,
                            41.551444
                        ],
                        [
                            -87.788453,
                            41.551509
                        ],
                        [
                            -87.788627,
                            41.551588
                        ],
                        [
                            -87.788907,
                            41.551738
                        ],
                        [
                            -87.789617,
                            41.552199
                        ],
                        [
                            -87.791009,
                            41.55317
                        ],
                        [
                            -87.791995,
                            41.553928
                        ],
                        [
                            -87.792135,
                            41.554073
                        ],
                        [
                            -87.792306,
                            41.554315
                        ],
                        [
                            -87.792435,
                            41.554646
                        ],
                        [
                            -87.792497,
                            41.555424
                        ],
                        [
                            -87.792543,
                            41.555497
                        ],
                        [
                            -87.792578,
                            41.556905
                        ],
                        [
                            -87.792582,
                            41.557485
                        ],
                        [
                            -87.792612,
                            41.558551
                        ],
                        [
                            -87.792821,
                            41.558544
                        ],
                        [
                            -87.793416,
                            41.558532
                        ],
                        [
                            -87.793585,
                            41.558528
                        ],
                        [
                            -87.79408,
                            41.558517
                        ],
                        [
                            -87.794813,
                            41.558501
                        ],
                        [
                            -87.796182,
                            41.558483
                        ],
                        [
                            -87.797283,
                            41.558476
                        ],
                        [
                            -87.797733,
                            41.558473
                        ],
                        [
                            -87.799193,
                            41.558463
                        ],
                        [
                            -87.800828,
                            41.558436
                        ],
                        [
                            -87.801608,
                            41.558424
                        ],
                        [
                            -87.802509,
                            41.558411
                        ],
                        [
                            -87.802934,
                            41.558405
                        ],
                        [
                            -87.803754,
                            41.558394
                        ],
                        [
                            -87.804242,
                            41.558388
                        ],
                        [
                            -87.805235,
                            41.558374
                        ],
                        [
                            -87.805391,
                            41.558372
                        ],
                        [
                            -87.805794,
                            41.558367
                        ],
                        [
                            -87.806614,
                            41.558358
                        ],
                        [
                            -87.807507,
                            41.558349
                        ],
                        [
                            -87.808644,
                            41.558336
                        ],
                        [
                            -87.808622,
                            41.558028
                        ],
                        [
                            -87.80825,
                            41.557812
                        ],
                        [
                            -87.808209,
                            41.557766
                        ],
                        [
                            -87.808183,
                            41.557224
                        ],
                        [
                            -87.808209,
                            41.557142
                        ],
                        [
                            -87.808265,
                            41.557077
                        ],
                        [
                            -87.808387,
                            41.556991
                        ],
                        [
                            -87.808628,
                            41.556862
                        ],
                        [
                            -87.8089,
                            41.556751
                        ],
                        [
                            -87.809253,
                            41.556683
                        ],
                        [
                            -87.810207,
                            41.556654
                        ]
                    ],
                    "type": "LineString"
                }
            }
        ]
    }
}